README.md
setup.cfg
setup.py
DharmeshDataMechanics/__init__.py
DharmeshDataMechanics.egg-info/PKG-INFO
DharmeshDataMechanics.egg-info/SOURCES.txt
DharmeshDataMechanics.egg-info/dependency_links.txt
DharmeshDataMechanics.egg-info/top_level.txt
DharmeshDataMechanics/CS591/__init__.py