Metadata-Version: 1.1
Name: DharmeshDataMechanics
Version: 1.0.6
Summary: CS 591 L1 scripts
Home-page: https://github.com/weirdindiankid/DharmeshDataMechanics
Author: Dharmesh Tarapore
Author-email: dharmesh@cs.bu.edu
License: UNKNOWN
Platform: UNKNOWN
Classifier: Development Status :: 3 - Alpha
Classifier: Intended Audience :: Developers
Classifier: Topic :: Software Development :: Build Tools
Classifier: License :: OSI Approved :: MIT License
Classifier: Programming Language :: Python :: 3
Classifier: Programming Language :: Python :: 3.4
Classifier: Programming Language :: Python :: 3.5
Classifier: Programming Language :: Python :: 3.6
